continental_cdk/__init__.py
continental_cdk/batch.py
continental_cdk/batch_fargate_construct.py
continental_cdk/iam.py
continental_cdk/iam_construct.py
continental_cdk-0.1.1.dist-info/LICENSE
continental_cdk-0.1.1.dist-info/METADATA
continental_cdk-0.1.1.dist-info/WHEEL
continental_cdk-0.1.1.dist-info/top_level.txt
continental_cdk-0.1.1.dist-info/RECORD
