Metadata-Version: 2.1
Name: continental-cdk
Version: 0.1.1
Summary: A Test package for Pip
Home-page: https://github.com/
Author: Wolfgang Unger
Author-email: wolfgang.r.unger@dxc.com
License: UNKNOWN
Platform: UNKNOWN
Classifier: Programming Language :: Python :: 3
Classifier: License :: OSI Approved :: MIT License
Classifier: Operating System :: OS Independent
License-File: LICENSE
